gguf_python/__init__.py
gguf_python/extractor.py
gguf_python/remover.py
gguf_python/renamer.py
gguf_python-0.0.4.dist-info/entry_points.txt
gguf_python-0.0.4.dist-info/LICENSE
gguf_python-0.0.4.dist-info/METADATA
gguf_python-0.0.4.dist-info/WHEEL
gguf_python-0.0.4.dist-info/RECORD
